{"contents":{"prettier":{"eslintIntegration":true},"search":{"exclude":{"**/node_modules/**":true,"**/bower_components/**":true,"**/dist/**":true,"**/tmp/**":true,"**/dlls/**":true,"**/libs/**":true,"**/coverage/**":true,"**/artifacts/**":true,"**/.git":true,"**/.DS_Store":true,"**/volumes/**":true}},"files":{"watcherExclude":{"**/.git/objects/**":true,"**/.git/subtree-cache/**":true,"**/node_modules/**":true,"**/dist/**":true,"**/coverage/**":true,"**/.git":true,"**/.DS_Store":true,"**/tmp/**":true,"**/dlls/**":true,"**/libs/**":true,"**/volumes/**":true}},"launch":{"version":"0.2.0","configurations":[{"type":"node","request":"launch","name":"Launch via NPM","runtimeExecutable":"npm","runtimeArgs":["run","script","remote","dev","--","-P","@fastory/api"],"port":9229,"console":"integratedTerminal"}]}},"overrides":[],"keys":["prettier.eslintIntegration","search.exclude","files.watcherExclude","launch.version","launch.configurations"]}